Metadata-Version: 2.1
Name: find-oper
Version: 1.1
Summary: select the operator covering the largest number of regions
Home-page: UNKNOWN
Author: nuqo888
Author-email: vladimirovich.aleksei.ru@gmail.com
License: MIT License
Platform: UNKNOWN
Requires-Python: >=3.5
